beancount_dkb/__init__.py
beancount_dkb/credit.py
beancount_dkb/ec.py
beancount_dkb/exceptions.py
beancount_dkb/extractors/__init__.py
beancount_dkb/extractors/credit.py
beancount_dkb/extractors/ec.py
beancount_dkb/helpers.py
beancount_dkb-1.7.0.dist-info/METADATA
beancount_dkb-1.7.0.dist-info/WHEEL
beancount_dkb-1.7.0.dist-info/licenses/LICENSE.txt
beancount_dkb-1.7.0.dist-info/RECORD
