Metadata-Version: 2.4
Name: beancount-dkb
Version: 1.7.0
Summary: Beancount Importer for DKB CSV exports
License: MIT
License-File: LICENSE.txt
Keywords: banking,beancount,cli-accounting,finance
Author: Siddhant Goel
Author-email: me@sgoel.dev
Requires-Python: >=3.9,<4.0
Classifier: Development Status :: 5 - Production/Stable
Classifier: Environment :: Console
Classifier: Environment :: Plugins
Classifier: Intended Audience :: End Users/Desktop
Classifier: Intended Audience :: Financial and Insurance Industry
Classifier: License :: OSI Approved :: MIT License
Classifier: Programming Language :: Python :: 3
Classifier: Programming Language :: Python :: 3.9
Classifier: Programming Language :: Python :: 3.10
Classifier: Programming Language :: Python :: 3.11
Classifier: Programming Language :: Python :: 3.12
Classifier: Programming Language :: Python :: 3.13
Classifier: Programming Language :: Python :: 3.14
Classifier: Programming Language :: Python :: 3 :: Only
Classifier: Topic :: Office/Business :: Financial
Classifier: Topic :: Office/Business :: Financial :: Accounting
Requires-Dist: babel (>=2.16.0,<3.0.0)
Requires-Dist: beancount (>=2.3.5)
Requires-Dist: beangulp (>=0.1.1,<0.3.0)
Project-URL: Repository, https://github.com/siddhantgoel/beancount-dkb
